{
  "db_name": "SQLite",
  "query": "\n        SELECT COUNT(*) as count\n        FROM music_play_eventz mpe\n        WHERE mpe.song_id IN (\n            SELECT song_id FROM artist_songz WHERE artist_id = ?\n        )\n        ",
  "describe": {
    "columns": [
      {
        "name": "count",
        "ordinal": 0,
        "type_info": "Integer"
      }
    ],
    "parameters": {
      "Right": 1
    },
    "nullable": [
      false
    ]
  },
  "hash": "4f54f6a081574dcf4639773eb9f871733f34dc75496478d3148518e32fa54845"
}
