{
  "db_name": "SQLite",
  "query": "\n        SELECT\n            album.id as \"album_id!: String\",\n            album.title as \"album_title!: String\",\n            (SELECT json_group_array(json_object('media_blob_id', ai.media_blob_id, 'is_primary', ai.is_primary, 'blob_type', mb.blob_type))\n             FROM album_imagez ai\n             JOIN media_blobz mb ON ai.media_blob_id = mb.id\n             WHERE ai.album_id = album.id) as \"images: String\",\n            fts.rank as \"fts_rank!: f64\",\n            COUNT(DISTINCT album_song.song_id) as \"song_count!: i64\",\n            rating.rating as \"user_rating: i64\",\n            CASE WHEN favorite.id IS NOT NULL THEN 1 ELSE 0 END as \"is_favorite!: i64\"\n        FROM albumz_fts fts\n        JOIN albumz album ON fts.album_id = album.id\n        LEFT JOIN album_songz album_song ON album_song.album_id = album.id\n        LEFT JOIN user_ratingz rating\n            ON rating.target_id = album.id\n            AND rating.target_type = 'album'\n            AND rating.user_id = ?\n        LEFT JOIN user_favoritez favorite\n            ON favorite.target_id = album.id\n            AND favorite.target_type = 'album'\n            AND favorite.user_id = ?\n        WHERE albumz_fts MATCH ?\n            AND album.deleted_at IS NULL\n            AND (rating.rating IS NULL OR rating.rating != 0)\n        GROUP BY album.id, album.title, fts.rank, rating.rating, favorite.id\n        ORDER BY fts.rank DESC\n        LIMIT 100\n        ",
  "describe": {
    "columns": [
      {
        "name": "album_id!: String",
        "ordinal": 0,
        "type_info": "Text"
      },
      {
        "name": "album_title!: String",
        "ordinal": 1,
        "type_info": "Text"
      },
      {
        "name": "images: String",
        "ordinal": 2,
        "type_info": "Null"
      },
      {
        "name": "fts_rank!: f64",
        "ordinal": 3,
        "type_info": "Null"
      },
      {
        "name": "song_count!: i64",
        "ordinal": 4,
        "type_info": "Null"
      },
      {
        "name": "user_rating: i64",
        "ordinal": 5,
        "type_info": "Integer"
      },
      {
        "name": "is_favorite!: i64",
        "ordinal": 6,
        "type_info": "Null"
      }
    ],
    "parameters": {
      "Right": 3
    },
    "nullable": [
      true,
      false,
      null,
      true,
      null,
      false,
      null
    ]
  },
  "hash": "7ef6df45241b5c9f286992ad7de5c770e8b4c417afc17165833710e7b1f809e3"
}
